{
  "raceInfo": {
    "raceId": 24496,
    "distance": "Long Course",
    "name": "Sound Rowers: Rat Island Regatta 2014 \u2014 Long Course",
    "displayURL": "https://www.webscorer.com/race?raceid=24496",
    "date": "Jun 21, 2014",
    "sport": "Paddling",
    "startTime": "Saturday, June 21, 2014 10:03 AM (GMT-7)",
    "country": "United States",
    "city": "Port Townsend",
    "pointsWeight": 0.852459
  },
  "racerResults": [
    {
      "originalPlace": 1,
      "canonicalName": "Rainer Storb",
      "craftCategory": "4x OW",
      "gender": "Male",
      "handicap": 1.0,
      "timeSeconds": 3422.8,
      "timeVersusPar": 0.0,
      "adjustedTimeSeconds": 3422.8,
      "adjustedTimeVersusPar": 0.0,
      "adjustedPlace": 0,
      "handicapPost": 1.0,
      "numRaces": 0,
      "handicapSequence": null,
      "handicapPointsSequence": null,
      "handicapStdDev": 0.0,
      "absoluteImprovement": 0.0,
      "parRacer": false
    },
    {
      "originalPlace": 2,
      "canonicalName": "Egor Klevak & Peter Turcan",
      "craftCategory": "HPK-2",
      "gender": "Male",
      "handicap": 1.0,
      "timeSeconds": 3529.9,
      "timeVersusPar": 0.0,
      "adjustedTimeSeconds": 3529.9,
      "adjustedTimeVersusPar": 0.0,
      "adjustedPlace": 0,
      "handicapPost": 1.0,
      "numRaces": 0,
      "handicapSequence": null,
      "handicapPointsSequence": null,
      "handicapStdDev": 0.0,
      "absoluteImprovement": 0.0,
      "parRacer": false
    },
    {
      "originalPlace": 3,
      "canonicalName": "Robert Meenk",
      "craftCategory": "1x OW-III",
      "gender": "Male",
      "handicap": 1.0,
      "timeSeconds": 3590.0,
      "timeVersusPar": 0.0,
      "adjustedTimeSeconds": 3590.0,
      "adjustedTimeVersusPar": 0.0,
      "adjustedPlace": 0,
      "handicapPost": 1.0,
      "numRaces": 0,
      "handicapSequence": null,
      "handicapPointsSequence": null,
      "handicapStdDev": 0.0,
      "absoluteImprovement": 0.0,
      "parRacer": false
    },
    {
      "originalPlace": 4,
      "canonicalName": "Sweet 16",
      "craftCategory": "8x+",
      "gender": "Female/Male",
      "handicap": 1.0,
      "timeSeconds": 3679.1,
      "timeVersusPar": 0.0,
      "adjustedTimeSeconds": 3679.1,
      "adjustedTimeVersusPar": 0.0,
      "adjustedPlace": 0,
      "handicapPost": 1.0,
      "numRaces": 0,
      "handicapSequence": null,
      "handicapPointsSequence": null,
      "handicapStdDev": 0.0,
      "absoluteImprovement": 0.0,
      "parRacer": false
    },
    {
      "originalPlace": 5,
      "canonicalName": "Jeff / Theresa Knakal",
      "craftCategory": "2x OW",
      "gender": "Female/Male",
      "handicap": 1.0,
      "timeSeconds": 3758.6,
      "timeVersusPar": 0.0,
      "adjustedTimeSeconds": 3758.6,
      "adjustedTimeVersusPar": 0.0,
      "adjustedPlace": 0,
      "handicapPost": 1.0,
      "numRaces": 0,
      "handicapSequence": null,
      "handicapPointsSequence": null,
      "handicapStdDev": 0.0,
      "absoluteImprovement": 0.0,
      "parRacer": false
    },
    {
      "originalPlace": 6,
      "canonicalName": "David Deschenes",
      "craftCategory": "1x Flatwater",
      "gender": "Male",
      "handicap": 1.0,
      "timeSeconds": 3811.1,
      "timeVersusPar": 0.0,
      "adjustedTimeSeconds": 3811.1,
      "adjustedTimeVersusPar": 0.0,
      "adjustedPlace": 0,
      "handicapPost": 1.0,
      "numRaces": 0,
      "handicapSequence": null,
      "handicapPointsSequence": null,
      "handicapStdDev": 0.0,
      "absoluteImprovement": 0.0,
      "parRacer": false
    },
    {
      "originalPlace": 7,
      "canonicalName": "ORU - Portland",
      "craftCategory": "8x+",
      "gender": "Female/Male",
      "handicap": 1.0,
      "timeSeconds": 3846.5,
      "timeVersusPar": 0.0,
      "adjustedTimeSeconds": 3846.5,
      "adjustedTimeVersusPar": 0.0,
      "adjustedPlace": 0,
      "handicapPost": 1.0,
      "numRaces": 0,
      "handicapSequence": null,
      "handicapPointsSequence": null,
      "handicapStdDev": 0.0,
      "absoluteImprovement": 0.0,
      "parRacer": false
    },
    {
      "originalPlace": 8,
      "canonicalName": "Nicholas Cryder",
      "craftCategory": "HPK",
      "gender": "Male",
      "handicap": 1.0,
      "timeSeconds": 3907.3,
      "timeVersusPar": 0.0,
      "adjustedTimeSeconds": 3907.3,
      "adjustedTimeVersusPar": 0.0,
      "adjustedPlace": 0,
      "handicapPost": 1.0,
      "numRaces": 0,
      "handicapSequence": null,
      "handicapPointsSequence": null,
      "handicapStdDev": 0.0,
      "absoluteImprovement": 0.0,
      "parRacer": false
    },
    {
      "originalPlace": 9,
      "canonicalName": "Don Kiesling",
      "craftCategory": "HPK",
      "gender": "Male",
      "handicap": 1.0,
      "timeSeconds": 3953.7,
      "timeVersusPar": 0.0,
      "adjustedTimeSeconds": 3953.7,
      "adjustedTimeVersusPar": 0.0,
      "adjustedPlace": 0,
      "handicapPost": 1.0,
      "numRaces": 0,
      "handicapSequence": null,
      "handicapPointsSequence": null,
      "handicapStdDev": 0.0,
      "absoluteImprovement": 0.0,
      "parRacer": false
    },
    {
      "originalPlace": 10,
      "canonicalName": "OPRA",
      "craftCategory": "2x Flatwater",
      "gender": "Female",
      "handicap": 1.0,
      "timeSeconds": 3983.6,
      "timeVersusPar": 0.0,
      "adjustedTimeSeconds": 3983.6,
      "adjustedTimeVersusPar": 0.0,
      "adjustedPlace": 0,
      "handicapPost": 1.0,
      "numRaces": 0,
      "handicapSequence": null,
      "handicapPointsSequence": null,
      "handicapStdDev": 0.0,
      "absoluteImprovement": 0.0,
      "parRacer": false
    },
    {
      "originalPlace": 11,
      "canonicalName": "Mark Miller/Jim Mason",
      "craftCategory": "2x OW",
      "gender": "Male",
      "handicap": 1.0,
      "timeSeconds": 4028.4,
      "timeVersusPar": 0.0,
      "adjustedTimeSeconds": 4028.4,
      "adjustedTimeVersusPar": 0.0,
      "adjustedPlace": 0,
      "handicapPost": 1.0,
      "numRaces": 0,
      "handicapSequence": null,
      "handicapPointsSequence": null,
      "handicapStdDev": 0.0,
      "absoluteImprovement": 0.0,
      "parRacer": false
    },
    {
      "originalPlace": 12,
      "canonicalName": "Tuf As Nails",
      "craftCategory": "8+",
      "gender": "Female",
      "handicap": 1.0,
      "timeSeconds": 4036.5,
      "timeVersusPar": 0.0,
      "adjustedTimeSeconds": 4036.5,
      "adjustedTimeVersusPar": 0.0,
      "adjustedPlace": 0,
      "handicapPost": 1.0,
      "numRaces": 0,
      "handicapSequence": null,
      "handicapPointsSequence": null,
      "handicapStdDev": 0.0,
      "absoluteImprovement": 0.0,
      "parRacer": false
    },
    {
      "originalPlace": 13,
      "canonicalName": "Kevin Olney",
      "craftCategory": "HPK",
      "gender": "Male",
      "handicap": 1.0,
      "timeSeconds": 4133.1,
      "timeVersusPar": 0.0,
      "adjustedTimeSeconds": 4133.1,
      "adjustedTimeVersusPar": 0.0,
      "adjustedPlace": 0,
      "handicapPost": 1.0,
      "numRaces": 0,
      "handicapSequence": null,
      "handicapPointsSequence": null,
      "handicapStdDev": 0.0,
      "absoluteImprovement": 0.0,
      "parRacer": false
    },
    {
      "originalPlace": 14,
      "canonicalName": "ORU",
      "craftCategory": "2x Flatwater",
      "gender": "Female/Male",
      "handicap": 1.0,
      "timeSeconds": 4148.0,
      "timeVersusPar": 0.0,
      "adjustedTimeSeconds": 4148.0,
      "adjustedTimeVersusPar": 0.0,
      "adjustedPlace": 0,
      "handicapPost": 1.0,
      "numRaces": 0,
      "handicapSequence": null,
      "handicapPointsSequence": null,
      "handicapStdDev": 0.0,
      "absoluteImprovement": 0.0,
      "parRacer": false
    },
    {
      "originalPlace": 15,
      "canonicalName": "Ele Paio",
      "craftCategory": "OC-6",
      "gender": "Female/Male",
      "handicap": 1.0,
      "timeSeconds": 4185.9,
      "timeVersusPar": 0.0,
      "adjustedTimeSeconds": 4185.9,
      "adjustedTimeVersusPar": 0.0,
      "adjustedPlace": 0,
      "handicapPost": 1.0,
      "numRaces": 0,
      "handicapSequence": null,
      "handicapPointsSequence": null,
      "handicapStdDev": 0.0,
      "absoluteImprovement": 0.0,
      "parRacer": false
    },
    {
      "originalPlace": 16,
      "canonicalName": "Coeur D'alene Rowing",
      "craftCategory": "2x OW",
      "gender": "Female/Male",
      "handicap": 1.0,
      "timeSeconds": 4193.6,
      "timeVersusPar": 0.0,
      "adjustedTimeSeconds": 4193.6,
      "adjustedTimeVersusPar": 0.0,
      "adjustedPlace": 0,
      "handicapPost": 1.0,
      "numRaces": 0,
      "handicapSequence": null,
      "handicapPointsSequence": null,
      "handicapStdDev": 0.0,
      "absoluteImprovement": 0.0,
      "parRacer": false
    },
    {
      "originalPlace": 17,
      "canonicalName": "John Heater",
      "craftCategory": "1x OW-III",
      "gender": "Male",
      "handicap": 1.0,
      "timeSeconds": 4217.5,
      "timeVersusPar": 0.0,
      "adjustedTimeSeconds": 4217.5,
      "adjustedTimeVersusPar": 0.0,
      "adjustedPlace": 0,
      "handicapPost": 1.0,
      "numRaces": 0,
      "handicapSequence": null,
      "handicapPointsSequence": null,
      "handicapStdDev": 0.0,
      "absoluteImprovement": 0.0,
      "parRacer": false
    },
    {
      "originalPlace": 18,
      "canonicalName": "Jeff Maloney",
      "craftCategory": "HPK",
      "gender": "Male",
      "handicap": 1.0,
      "timeSeconds": 4276.8,
      "timeVersusPar": 0.0,
      "adjustedTimeSeconds": 4276.8,
      "adjustedTimeVersusPar": 0.0,
      "adjustedPlace": 0,
      "handicapPost": 1.0,
      "numRaces": 0,
      "handicapSequence": null,
      "handicapPointsSequence": null,
      "handicapStdDev": 0.0,
      "absoluteImprovement": 0.0,
      "parRacer": false
    },
    {
      "originalPlace": 19,
      "canonicalName": "Mike Walsh",
      "craftCategory": "1x OW-III",
      "gender": "Male",
      "handicap": 1.0,
      "timeSeconds": 4285.6,
      "timeVersusPar": 0.0,
      "adjustedTimeSeconds": 4285.6,
      "adjustedTimeVersusPar": 0.0,
      "adjustedPlace": 0,
      "handicapPost": 1.0,
      "numRaces": 0,
      "handicapSequence": null,
      "handicapPointsSequence": null,
      "handicapStdDev": 0.0,
      "absoluteImprovement": 0.0,
      "parRacer": false
    },
    {
      "originalPlace": 20,
      "canonicalName": "Michael Medler",
      "craftCategory": "HPK-2",
      "gender": "Female/Male",
      "handicap": 1.0,
      "timeSeconds": 4330.5,
      "timeVersusPar": 0.0,
      "adjustedTimeSeconds": 4330.5,
      "adjustedTimeVersusPar": 0.0,
      "adjustedPlace": 0,
      "handicapPost": 1.0,
      "numRaces": 0,
      "handicapSequence": null,
      "handicapPointsSequence": null,
      "handicapStdDev": 0.0,
      "absoluteImprovement": 0.0,
      "parRacer": false
    },
    {
      "originalPlace": 21,
      "canonicalName": "Robin Pike",
      "craftCategory": "1x OW-III",
      "gender": "Female",
      "handicap": 1.0,
      "timeSeconds": 4345.6,
      "timeVersusPar": 0.0,
      "adjustedTimeSeconds": 4345.6,
      "adjustedTimeVersusPar": 0.0,
      "adjustedPlace": 0,
      "handicapPost": 1.0,
      "numRaces": 0,
      "handicapSequence": null,
      "handicapPointsSequence": null,
      "handicapStdDev": 0.0,
      "absoluteImprovement": 0.0,
      "parRacer": false
    },
    {
      "originalPlace": 22,
      "canonicalName": "Riverside",
      "craftCategory": "4x",
      "gender": "Female",
      "handicap": 1.0,
      "timeSeconds": 4365.3,
      "timeVersusPar": 0.0,
      "adjustedTimeSeconds": 4365.3,
      "adjustedTimeVersusPar": 0.0,
      "adjustedPlace": 0,
      "handicapPost": 1.0,
      "numRaces": 0,
      "handicapSequence": null,
      "handicapPointsSequence": null,
      "handicapStdDev": 0.0,
      "absoluteImprovement": 0.0,
      "parRacer": false
    },
    {
      "originalPlace": 23,
      "canonicalName": "Frank C.",
      "craftCategory": "4x",
      "gender": "Female/Male",
      "handicap": 1.0,
      "timeSeconds": 4448.6,
      "timeVersusPar": 0.0,
      "adjustedTimeSeconds": 4448.6,
      "adjustedTimeVersusPar": 0.0,
      "adjustedPlace": 0,
      "handicapPost": 1.0,
      "numRaces": 0,
      "handicapSequence": null,
      "handicapPointsSequence": null,
      "handicapStdDev": 0.0,
      "absoluteImprovement": 0.0,
      "parRacer": false
    },
    {
      "originalPlace": 24,
      "canonicalName": "Russell Brown",
      "craftCategory": "HPK",
      "gender": "Male",
      "handicap": 1.0,
      "timeSeconds": 4470.9,
      "timeVersusPar": 0.0,
      "adjustedTimeSeconds": 4470.9,
      "adjustedTimeVersusPar": 0.0,
      "adjustedPlace": 0,
      "handicapPost": 1.0,
      "numRaces": 0,
      "handicapSequence": null,
      "handicapPointsSequence": null,
      "handicapStdDev": 0.0,
      "absoluteImprovement": 0.0,
      "parRacer": false
    },
    {
      "originalPlace": 25,
      "canonicalName": "Paul Noyes",
      "craftCategory": "1x OW-III",
      "gender": "Male",
      "handicap": 1.0,
      "timeSeconds": 4528.9,
      "timeVersusPar": 0.0,
      "adjustedTimeSeconds": 4528.9,
      "adjustedTimeVersusPar": 0.0,
      "adjustedPlace": 0,
      "handicapPost": 1.0,
      "numRaces": 0,
      "handicapSequence": null,
      "handicapPointsSequence": null,
      "handicapStdDev": 0.0,
      "absoluteImprovement": 0.0,
      "parRacer": false
    },
    {
      "originalPlace": 26,
      "canonicalName": "Bill Jaquette",
      "craftCategory": "1x OW-III",
      "gender": "Male",
      "handicap": 1.0,
      "timeSeconds": 4635.6,
      "timeVersusPar": 0.0,
      "adjustedTimeSeconds": 4635.6,
      "adjustedTimeVersusPar": 0.0,
      "adjustedPlace": 0,
      "handicapPost": 1.0,
      "numRaces": 0,
      "handicapSequence": null,
      "handicapPointsSequence": null,
      "handicapStdDev": 0.0,
      "absoluteImprovement": 0.0,
      "parRacer": false
    },
    {
      "originalPlace": 27,
      "canonicalName": "Bogie",
      "craftCategory": "4x",
      "gender": "Female/Male",
      "handicap": 1.0,
      "timeSeconds": 4667.0,
      "timeVersusPar": 0.0,
      "adjustedTimeSeconds": 4667.0,
      "adjustedTimeVersusPar": 0.0,
      "adjustedPlace": 0,
      "handicapPost": 1.0,
      "numRaces": 0,
      "handicapSequence": null,
      "handicapPointsSequence": null,
      "handicapStdDev": 0.0,
      "absoluteImprovement": 0.0,
      "parRacer": false
    },
    {
      "originalPlace": 28,
      "canonicalName": "Charley Kanieski",
      "craftCategory": "1x OW-III",
      "gender": "Male",
      "handicap": 1.0,
      "timeSeconds": 4721.4,
      "timeVersusPar": 0.0,
      "adjustedTimeSeconds": 4721.4,
      "adjustedTimeVersusPar": 0.0,
      "adjustedPlace": 0,
      "handicapPost": 1.0,
      "numRaces": 0,
      "handicapSequence": null,
      "handicapPointsSequence": null,
      "handicapStdDev": 0.0,
      "absoluteImprovement": 0.0,
      "parRacer": false
    },
    {
      "originalPlace": 29,
      "canonicalName": "Dose",
      "craftCategory": "4x",
      "gender": "Female",
      "handicap": 1.0,
      "timeSeconds": 4747.7,
      "timeVersusPar": 0.0,
      "adjustedTimeSeconds": 4747.7,
      "adjustedTimeVersusPar": 0.0,
      "adjustedPlace": 0,
      "handicapPost": 1.0,
      "numRaces": 0,
      "handicapSequence": null,
      "handicapPointsSequence": null,
      "handicapStdDev": 0.0,
      "absoluteImprovement": 0.0,
      "parRacer": false
    },
    {
      "originalPlace": 30,
      "canonicalName": "Dave McWethy",
      "craftCategory": "1x OW-III",
      "gender": "Male",
      "handicap": 1.0,
      "timeSeconds": 4772.1,
      "timeVersusPar": 0.0,
      "adjustedTimeSeconds": 4772.1,
      "adjustedTimeVersusPar": 0.0,
      "adjustedPlace": 0,
      "handicapPost": 1.0,
      "numRaces": 0,
      "handicapSequence": null,
      "handicapPointsSequence": null,
      "handicapStdDev": 0.0,
      "absoluteImprovement": 0.0,
      "parRacer": false
    },
    {
      "originalPlace": 31,
      "canonicalName": "Herb Weisse",
      "craftCategory": "1x OW-III",
      "gender": "Male",
      "handicap": 1.0,
      "timeSeconds": 4799.9,
      "timeVersusPar": 0.0,
      "adjustedTimeSeconds": 4799.9,
      "adjustedTimeVersusPar": 0.0,
      "adjustedPlace": 0,
      "handicapPost": 1.0,
      "numRaces": 0,
      "handicapSequence": null,
      "handicapPointsSequence": null,
      "handicapStdDev": 0.0,
      "absoluteImprovement": 0.0,
      "parRacer": false
    },
    {
      "originalPlace": 32,
      "canonicalName": "David Mittmann",
      "craftCategory": "1x OW-III",
      "gender": "Male",
      "handicap": 1.0,
      "timeSeconds": 4813.7,
      "timeVersusPar": 0.0,
      "adjustedTimeSeconds": 4813.7,
      "adjustedTimeVersusPar": 0.0,
      "adjustedPlace": 0,
      "handicapPost": 1.0,
      "numRaces": 0,
      "handicapSequence": null,
      "handicapPointsSequence": null,
      "handicapStdDev": 0.0,
      "absoluteImprovement": 0.0,
      "parRacer": false
    },
    {
      "originalPlace": 33,
      "canonicalName": "Chris/Callie Johnston",
      "craftCategory": "2x OW",
      "gender": "Female/Male",
      "handicap": 1.0,
      "timeSeconds": 4833.0,
      "timeVersusPar": 0.0,
      "adjustedTimeSeconds": 4833.0,
      "adjustedTimeVersusPar": 0.0,
      "adjustedPlace": 0,
      "handicapPost": 1.0,
      "numRaces": 0,
      "handicapSequence": null,
      "handicapPointsSequence": null,
      "handicapStdDev": 0.0,
      "absoluteImprovement": 0.0,
      "parRacer": false
    },
    {
      "originalPlace": 34,
      "canonicalName": "Lorna Smith",
      "craftCategory": "4x",
      "gender": "Female",
      "handicap": 1.0,
      "timeSeconds": 4850.4,
      "timeVersusPar": 0.0,
      "adjustedTimeSeconds": 4850.4,
      "adjustedTimeVersusPar": 0.0,
      "adjustedPlace": 0,
      "handicapPost": 1.0,
      "numRaces": 0,
      "handicapSequence": null,
      "handicapPointsSequence": null,
      "handicapStdDev": 0.0,
      "absoluteImprovement": 0.0,
      "parRacer": false
    },
    {
      "originalPlace": 35,
      "canonicalName": "Michael Lampi",
      "craftCategory": "Pedalboat",
      "gender": "Male",
      "handicap": 1.0,
      "timeSeconds": 4950.2,
      "timeVersusPar": 0.0,
      "adjustedTimeSeconds": 4950.2,
      "adjustedTimeVersusPar": 0.0,
      "adjustedPlace": 0,
      "handicapPost": 1.0,
      "numRaces": 0,
      "handicapSequence": null,
      "handicapPointsSequence": null,
      "handicapStdDev": 0.0,
      "absoluteImprovement": 0.0,
      "parRacer": false
    },
    {
      "originalPlace": 36,
      "canonicalName": "Sue Kenney",
      "craftCategory": "4+",
      "gender": "Female",
      "handicap": 1.0,
      "timeSeconds": 5004.0,
      "timeVersusPar": 0.0,
      "adjustedTimeSeconds": 5004.0,
      "adjustedTimeVersusPar": 0.0,
      "adjustedPlace": 0,
      "handicapPost": 1.0,
      "numRaces": 0,
      "handicapSequence": null,
      "handicapPointsSequence": null,
      "handicapStdDev": 0.0,
      "absoluteImprovement": 0.0,
      "parRacer": false
    },
    {
      "originalPlace": 37,
      "canonicalName": "Colleen Brastad",
      "craftCategory": "1x OW-III",
      "gender": "Female",
      "handicap": 1.0,
      "timeSeconds": 5096.8,
      "timeVersusPar": 0.0,
      "adjustedTimeSeconds": 5096.8,
      "adjustedTimeVersusPar": 0.0,
      "adjustedPlace": 0,
      "handicapPost": 1.0,
      "numRaces": 0,
      "handicapSequence": null,
      "handicapPointsSequence": null,
      "handicapStdDev": 0.0,
      "absoluteImprovement": 0.0,
      "parRacer": false
    },
    {
      "originalPlace": 38,
      "canonicalName": "Traci Cole",
      "craftCategory": "HPK",
      "gender": "Female",
      "handicap": 1.0,
      "timeSeconds": 5192.9,
      "timeVersusPar": 0.0,
      "adjustedTimeSeconds": 5192.9,
      "adjustedTimeVersusPar": 0.0,
      "adjustedPlace": 0,
      "handicapPost": 1.0,
      "numRaces": 0,
      "handicapSequence": null,
      "handicapPointsSequence": null,
      "handicapStdDev": 0.0,
      "absoluteImprovement": 0.0,
      "parRacer": false
    },
    {
      "originalPlace": 39,
      "canonicalName": "Gabe Wegener",
      "craftCategory": "1x Flatwater",
      "gender": "Male",
      "handicap": 1.0,
      "timeSeconds": 5376.7,
      "timeVersusPar": 0.0,
      "adjustedTimeSeconds": 5376.7,
      "adjustedTimeVersusPar": 0.0,
      "adjustedPlace": 0,
      "handicapPost": 1.0,
      "numRaces": 0,
      "handicapSequence": null,
      "handicapPointsSequence": null,
      "handicapStdDev": 0.0,
      "absoluteImprovement": 0.0,
      "parRacer": false
    },
    {
      "originalPlace": 40,
      "canonicalName": "Shane Baker",
      "craftCategory": "HPK",
      "gender": "Male",
      "handicap": 1.0,
      "timeSeconds": 5475.2,
      "timeVersusPar": 0.0,
      "adjustedTimeSeconds": 5475.2,
      "adjustedTimeVersusPar": 0.0,
      "adjustedPlace": 0,
      "handicapPost": 1.0,
      "numRaces": 0,
      "handicapSequence": null,
      "handicapPointsSequence": null,
      "handicapStdDev": 0.0,
      "absoluteImprovement": 0.0,
      "parRacer": false
    },
    {
      "originalPlace": 41,
      "canonicalName": "Riley O'Brien",
      "craftCategory": "1x OW-II",
      "gender": "Male",
      "handicap": 1.0,
      "timeSeconds": 5521.0,
      "timeVersusPar": 0.0,
      "adjustedTimeSeconds": 5521.0,
      "adjustedTimeVersusPar": 0.0,
      "adjustedPlace": 0,
      "handicapPost": 1.0,
      "numRaces": 0,
      "handicapSequence": null,
      "handicapPointsSequence": null,
      "handicapStdDev": 0.0,
      "absoluteImprovement": 0.0,
      "parRacer": false
    },
    {
      "originalPlace": 42,
      "canonicalName": "Friendship",
      "craftCategory": "8+",
      "gender": "Female/Male",
      "handicap": 1.0,
      "timeSeconds": 5550.4,
      "timeVersusPar": 0.0,
      "adjustedTimeSeconds": 5550.4,
      "adjustedTimeVersusPar": 0.0,
      "adjustedPlace": 0,
      "handicapPost": 1.0,
      "numRaces": 0,
      "handicapSequence": null,
      "handicapPointsSequence": null,
      "handicapStdDev": 0.0,
      "absoluteImprovement": 0.0,
      "parRacer": false
    },
    {
      "originalPlace": 43,
      "canonicalName": "Pat Johnson",
      "craftCategory": "1x OW-III",
      "gender": "Female",
      "handicap": 1.0,
      "timeSeconds": 5677.8,
      "timeVersusPar": 0.0,
      "adjustedTimeSeconds": 5677.8,
      "adjustedTimeVersusPar": 0.0,
      "adjustedPlace": 0,
      "handicapPost": 1.0,
      "numRaces": 0,
      "handicapSequence": null,
      "handicapPointsSequence": null,
      "handicapStdDev": 0.0,
      "absoluteImprovement": 0.0,
      "parRacer": false
    },
    {
      "originalPlace": 44,
      "canonicalName": "Kent Zimmerman",
      "craftCategory": "1x OW-I",
      "gender": "Male",
      "handicap": 1.0,
      "timeSeconds": 6493.8,
      "timeVersusPar": 0.0,
      "adjustedTimeSeconds": 6493.8,
      "adjustedTimeVersusPar": 0.0,
      "adjustedPlace": 0,
      "handicapPost": 1.0,
      "numRaces": 0,
      "handicapSequence": null,
      "handicapPointsSequence": null,
      "handicapStdDev": 0.0,
      "absoluteImprovement": 0.0,
      "parRacer": false
    },
    {
      "originalPlace": 45,
      "canonicalName": "Mc Daniel / Knudsen",
      "craftCategory": "SK-2",
      "gender": "Male",
      "handicap": 1.0,
      "timeSeconds": 6656.7,
      "timeVersusPar": 0.0,
      "adjustedTimeSeconds": 6656.7,
      "adjustedTimeVersusPar": 0.0,
      "adjustedPlace": 0,
      "handicapPost": 1.0,
      "numRaces": 0,
      "handicapSequence": null,
      "handicapPointsSequence": null,
      "handicapStdDev": 0.0,
      "absoluteImprovement": 0.0,
      "parRacer": false
    },
    {
      "originalPlace": 46,
      "canonicalName": "Carrie Weise",
      "craftCategory": "1x OW-II",
      "gender": "Female",
      "handicap": 1.0,
      "timeSeconds": 8100.0,
      "timeVersusPar": 0.0,
      "adjustedTimeSeconds": 8100.0,
      "adjustedTimeVersusPar": 0.0,
      "adjustedPlace": 0,
      "handicapPost": 1.0,
      "numRaces": 0,
      "handicapSequence": null,
      "handicapPointsSequence": null,
      "handicapStdDev": 0.0,
      "absoluteImprovement": 0.0,
      "parRacer": false
    },
    {
      "originalPlace": 47,
      "canonicalName": "Bob Rhoades",
      "craftCategory": "1x OW-III",
      "gender": "Male",
      "handicap": 1.0,
      "timeSeconds": 8263.0,
      "timeVersusPar": 0.0,
      "adjustedTimeSeconds": 8263.0,
      "adjustedTimeVersusPar": 0.0,
      "adjustedPlace": 0,
      "handicapPost": 1.0,
      "numRaces": 0,
      "handicapSequence": null,
      "handicapPointsSequence": null,
      "handicapStdDev": 0.0,
      "absoluteImprovement": 0.0,
      "parRacer": false
    },
    {
      "originalPlace": 48,
      "canonicalName": "Arran Stark",
      "craftCategory": "SUP",
      "gender": "Male",
      "handicap": 1.0,
      "timeSeconds": 8530.3,
      "timeVersusPar": 0.0,
      "adjustedTimeSeconds": 8530.3,
      "adjustedTimeVersusPar": 0.0,
      "adjustedPlace": 0,
      "handicapPost": 1.0,
      "numRaces": 0,
      "handicapSequence": null,
      "handicapPointsSequence": null,
      "handicapStdDev": 0.0,
      "absoluteImprovement": 0.0,
      "parRacer": false
    },
    {
      "originalPlace": 49,
      "canonicalName": "Sam Cunard",
      "craftCategory": "SUP",
      "gender": "Male",
      "handicap": 1.0,
      "timeSeconds": 8542.6,
      "timeVersusPar": 0.0,
      "adjustedTimeSeconds": 8542.6,
      "adjustedTimeVersusPar": 0.0,
      "adjustedPlace": 0,
      "handicapPost": 1.0,
      "numRaces": 0,
      "handicapSequence": null,
      "handicapPointsSequence": null,
      "handicapStdDev": 0.0,
      "absoluteImprovement": 0.0,
      "parRacer": false
    },
    {
      "originalPlace": 50,
      "canonicalName": "Alison Cunard",
      "craftCategory": "SUP",
      "gender": "Female",
      "handicap": 1.0,
      "timeSeconds": 9967.1,
      "timeVersusPar": 0.0,
      "adjustedTimeSeconds": 9967.1,
      "adjustedTimeVersusPar": 0.0,
      "adjustedPlace": 0,
      "handicapPost": 1.0,
      "numRaces": 0,
      "handicapSequence": null,
      "handicapPointsSequence": null,
      "handicapStdDev": 0.0,
      "absoluteImprovement": 0.0,
      "parRacer": false
    },
    {
      "originalPlace": 51,
      "canonicalName": "Holly Cunard",
      "craftCategory": "SUP",
      "gender": "Female",
      "handicap": 1.0,
      "timeSeconds": 11263.0,
      "timeVersusPar": 0.0,
      "adjustedTimeSeconds": 11263.0,
      "adjustedTimeVersusPar": 0.0,
      "adjustedPlace": 0,
      "handicapPost": 1.0,
      "numRaces": 0,
      "handicapSequence": null,
      "handicapPointsSequence": null,
      "handicapStdDev": 0.0,
      "absoluteImprovement": 0.0,
      "parRacer": false
    },
    {
      "originalPlace": 52,
      "canonicalName": "Bruce Cunard",
      "craftCategory": "SUP",
      "gender": "Male",
      "handicap": 1.0,
      "timeSeconds": 11266.2,
      "timeVersusPar": 0.0,
      "adjustedTimeSeconds": 11266.2,
      "adjustedTimeVersusPar": 0.0,
      "adjustedPlace": 0,
      "handicapPost": 1.0,
      "numRaces": 0,
      "handicapSequence": null,
      "handicapPointsSequence": null,
      "handicapStdDev": 0.0,
      "absoluteImprovement": 0.0,
      "parRacer": false
    }
  ]
}