{
  "raceInfo": {
    "raceId": 14077,
    "distance": "14.3 miles",
    "name": "Sound Rowers: Mercer Island 2013 \u2014 14.3 miles",
    "displayURL": "https://www.webscorer.com/race?raceid=14077",
    "date": "Oct 5, 2013",
    "sport": "Paddling",
    "startTime": "Saturday, October 5, 2013 10:00 AM (GMT-7)",
    "country": "United States",
    "city": "Seattle",
    "pointsWeight": 0.462963
  },
  "racerResults": [
    {
      "originalPlace": 1,
      "canonicalName": "Greg Barton",
      "craftCategory": "M HPK",
      "gender": "Unknown",
      "handicap": 1.0,
      "timeSeconds": 6115.8,
      "timeVersusPar": 0.0,
      "adjustedTimeSeconds": 6115.8,
      "adjustedTimeVersusPar": 0.0,
      "adjustedPlace": 0,
      "handicapPost": 1.0,
      "numRaces": 0,
      "handicapSequence": null,
      "handicapPointsSequence": null,
      "handicapStdDev": 0.0,
      "absoluteImprovement": 0.0,
      "parRacer": false
    },
    {
      "originalPlace": 2,
      "canonicalName": "Jason Cross / Egor Klevak",
      "craftCategory": "M HPK2",
      "gender": "Unknown",
      "handicap": 1.0,
      "timeSeconds": 6116.4,
      "timeVersusPar": 0.0,
      "adjustedTimeSeconds": 6116.4,
      "adjustedTimeVersusPar": 0.0,
      "adjustedPlace": 0,
      "handicapPost": 1.0,
      "numRaces": 0,
      "handicapSequence": null,
      "handicapPointsSequence": null,
      "handicapStdDev": 0.0,
      "absoluteImprovement": 0.0,
      "parRacer": false
    },
    {
      "originalPlace": 3,
      "canonicalName": "Juraj Osusky & Peter Turcan",
      "craftCategory": "M HPK2",
      "gender": "Unknown",
      "handicap": 1.0,
      "timeSeconds": 6136.9,
      "timeVersusPar": 0.0,
      "adjustedTimeSeconds": 6136.9,
      "adjustedTimeVersusPar": 0.0,
      "adjustedPlace": 0,
      "handicapPost": 1.0,
      "numRaces": 0,
      "handicapSequence": null,
      "handicapPointsSequence": null,
      "handicapStdDev": 0.0,
      "absoluteImprovement": 0.0,
      "parRacer": false
    },
    {
      "originalPlace": 4,
      "canonicalName": "Peter Hirtle",
      "craftCategory": "M 1x-Flatwater",
      "gender": "Unknown",
      "handicap": 1.0,
      "timeSeconds": 6585.8,
      "timeVersusPar": 0.0,
      "adjustedTimeSeconds": 6585.8,
      "adjustedTimeVersusPar": 0.0,
      "adjustedPlace": 0,
      "handicapPost": 1.0,
      "numRaces": 0,
      "handicapSequence": null,
      "handicapPointsSequence": null,
      "handicapStdDev": 0.0,
      "absoluteImprovement": 0.0,
      "parRacer": false
    },
    {
      "originalPlace": 5,
      "canonicalName": "Jeff / Theresa Knakal",
      "craftCategory": "Mx 2x-Flatwater",
      "gender": "Unknown",
      "handicap": 1.0,
      "timeSeconds": 6586.9,
      "timeVersusPar": 0.0,
      "adjustedTimeSeconds": 6586.9,
      "adjustedTimeVersusPar": 0.0,
      "adjustedPlace": 0,
      "handicapPost": 1.0,
      "numRaces": 0,
      "handicapSequence": null,
      "handicapPointsSequence": null,
      "handicapStdDev": 0.0,
      "absoluteImprovement": 0.0,
      "parRacer": false
    },
    {
      "originalPlace": 6,
      "canonicalName": "Rainer/Adrian Storb",
      "craftCategory": "M 2x-OW",
      "gender": "Unknown",
      "handicap": 1.0,
      "timeSeconds": 6681.3,
      "timeVersusPar": 0.0,
      "adjustedTimeSeconds": 6681.3,
      "adjustedTimeVersusPar": 0.0,
      "adjustedPlace": 0,
      "handicapPost": 1.0,
      "numRaces": 0,
      "handicapSequence": null,
      "handicapPointsSequence": null,
      "handicapStdDev": 0.0,
      "absoluteImprovement": 0.0,
      "parRacer": false
    },
    {
      "originalPlace": 7,
      "canonicalName": "Dean Bumstead",
      "craftCategory": "M HPK",
      "gender": "Unknown",
      "handicap": 1.0,
      "timeSeconds": 7183.7,
      "timeVersusPar": 0.0,
      "adjustedTimeSeconds": 7183.7,
      "adjustedTimeVersusPar": 0.0,
      "adjustedPlace": 0,
      "handicapPost": 1.0,
      "numRaces": 0,
      "handicapSequence": null,
      "handicapPointsSequence": null,
      "handicapStdDev": 0.0,
      "absoluteImprovement": 0.0,
      "parRacer": false
    },
    {
      "originalPlace": 8,
      "canonicalName": "Chris Dobrovolny",
      "craftCategory": "M HPK",
      "gender": "Unknown",
      "handicap": 1.0,
      "timeSeconds": 7188.1,
      "timeVersusPar": 0.0,
      "adjustedTimeSeconds": 7188.1,
      "adjustedTimeVersusPar": 0.0,
      "adjustedPlace": 0,
      "handicapPost": 1.0,
      "numRaces": 0,
      "handicapSequence": null,
      "handicapPointsSequence": null,
      "handicapStdDev": 0.0,
      "absoluteImprovement": 0.0,
      "parRacer": false
    },
    {
      "originalPlace": 9,
      "canonicalName": "Marc Whitlock",
      "craftCategory": "M HPK",
      "gender": "Unknown",
      "handicap": 1.0,
      "timeSeconds": 7374.5,
      "timeVersusPar": 0.0,
      "adjustedTimeSeconds": 7374.5,
      "adjustedTimeVersusPar": 0.0,
      "adjustedPlace": 0,
      "handicapPost": 1.0,
      "numRaces": 0,
      "handicapSequence": null,
      "handicapPointsSequence": null,
      "handicapStdDev": 0.0,
      "absoluteImprovement": 0.0,
      "parRacer": false
    },
    {
      "originalPlace": 10,
      "canonicalName": "Steve Scoggins",
      "craftCategory": "M HPK",
      "gender": "Unknown",
      "handicap": 1.0,
      "timeSeconds": 7443.0,
      "timeVersusPar": 0.0,
      "adjustedTimeSeconds": 7443.0,
      "adjustedTimeVersusPar": 0.0,
      "adjustedPlace": 0,
      "handicapPost": 1.0,
      "numRaces": 0,
      "handicapSequence": null,
      "handicapPointsSequence": null,
      "handicapStdDev": 0.0,
      "absoluteImprovement": 0.0,
      "parRacer": false
    },
    {
      "originalPlace": 11,
      "canonicalName": "Tom Kreyche",
      "craftCategory": "M 1x-OWIII",
      "gender": "Unknown",
      "handicap": 1.0,
      "timeSeconds": 7515.1,
      "timeVersusPar": 0.0,
      "adjustedTimeSeconds": 7515.1,
      "adjustedTimeVersusPar": 0.0,
      "adjustedPlace": 0,
      "handicapPost": 1.0,
      "numRaces": 0,
      "handicapSequence": null,
      "handicapPointsSequence": null,
      "handicapStdDev": 0.0,
      "absoluteImprovement": 0.0,
      "parRacer": false
    },
    {
      "originalPlace": 12,
      "canonicalName": "Greg Bawden",
      "craftCategory": "M HPK",
      "gender": "Unknown",
      "handicap": 1.0,
      "timeSeconds": 7560.7,
      "timeVersusPar": 0.0,
      "adjustedTimeSeconds": 7560.7,
      "adjustedTimeVersusPar": 0.0,
      "adjustedPlace": 0,
      "handicapPost": 1.0,
      "numRaces": 0,
      "handicapSequence": null,
      "handicapPointsSequence": null,
      "handicapStdDev": 0.0,
      "absoluteImprovement": 0.0,
      "parRacer": false
    },
    {
      "originalPlace": 13,
      "canonicalName": "Michael Dee",
      "craftCategory": "M HPK",
      "gender": "Unknown",
      "handicap": 1.0,
      "timeSeconds": 7563.8,
      "timeVersusPar": 0.0,
      "adjustedTimeSeconds": 7563.8,
      "adjustedTimeVersusPar": 0.0,
      "adjustedPlace": 0,
      "handicapPost": 1.0,
      "numRaces": 0,
      "handicapSequence": null,
      "handicapPointsSequence": null,
      "handicapStdDev": 0.0,
      "absoluteImprovement": 0.0,
      "parRacer": false
    },
    {
      "originalPlace": 14,
      "canonicalName": "Bill Jaquette",
      "craftCategory": "M 1x-OWIII",
      "gender": "Unknown",
      "handicap": 1.0,
      "timeSeconds": 7606.5,
      "timeVersusPar": 0.0,
      "adjustedTimeSeconds": 7606.5,
      "adjustedTimeVersusPar": 0.0,
      "adjustedPlace": 0,
      "handicapPost": 1.0,
      "numRaces": 0,
      "handicapSequence": null,
      "handicapPointsSequence": null,
      "handicapStdDev": 0.0,
      "absoluteImprovement": 0.0,
      "parRacer": false
    },
    {
      "originalPlace": 15,
      "canonicalName": "David Scherrer",
      "craftCategory": "M HPK",
      "gender": "Unknown",
      "handicap": 1.0,
      "timeSeconds": 7785.1,
      "timeVersusPar": 0.0,
      "adjustedTimeSeconds": 7785.1,
      "adjustedTimeVersusPar": 0.0,
      "adjustedPlace": 0,
      "handicapPost": 1.0,
      "numRaces": 0,
      "handicapSequence": null,
      "handicapPointsSequence": null,
      "handicapStdDev": 0.0,
      "absoluteImprovement": 0.0,
      "parRacer": false
    },
    {
      "originalPlace": 16,
      "canonicalName": "Vern Heikkila/Jeffrey Wong",
      "craftCategory": "M OC2",
      "gender": "Unknown",
      "handicap": 1.0,
      "timeSeconds": 8170.9,
      "timeVersusPar": 0.0,
      "adjustedTimeSeconds": 8170.9,
      "adjustedTimeVersusPar": 0.0,
      "adjustedPlace": 0,
      "handicapPost": 1.0,
      "numRaces": 0,
      "handicapSequence": null,
      "handicapPointsSequence": null,
      "handicapStdDev": 0.0,
      "absoluteImprovement": 0.0,
      "parRacer": false
    },
    {
      "originalPlace": 17,
      "canonicalName": "Roger Lamb",
      "craftCategory": "M HPK",
      "gender": "Unknown",
      "handicap": 1.0,
      "timeSeconds": 8182.2,
      "timeVersusPar": 0.0,
      "adjustedTimeSeconds": 8182.2,
      "adjustedTimeVersusPar": 0.0,
      "adjustedPlace": 0,
      "handicapPost": 1.0,
      "numRaces": 0,
      "handicapSequence": null,
      "handicapPointsSequence": null,
      "handicapStdDev": 0.0,
      "absoluteImprovement": 0.0,
      "parRacer": false
    },
    {
      "originalPlace": 18,
      "canonicalName": "Seattle Flying Dragons (Fire)",
      "craftCategory": "Mx Dragon",
      "gender": "Unknown",
      "handicap": 1.0,
      "timeSeconds": 9002.8,
      "timeVersusPar": 0.0,
      "adjustedTimeSeconds": 9002.8,
      "adjustedTimeVersusPar": 0.0,
      "adjustedPlace": 0,
      "handicapPost": 1.0,
      "numRaces": 0,
      "handicapSequence": null,
      "handicapPointsSequence": null,
      "handicapStdDev": 0.0,
      "absoluteImprovement": 0.0,
      "parRacer": false
    },
    {
      "originalPlace": 19,
      "canonicalName": "Walter Horton",
      "craftCategory": "M FSK",
      "gender": "Unknown",
      "handicap": 1.0,
      "timeSeconds": 9314.2,
      "timeVersusPar": 0.0,
      "adjustedTimeSeconds": 9314.2,
      "adjustedTimeVersusPar": 0.0,
      "adjustedPlace": 0,
      "handicapPost": 1.0,
      "numRaces": 0,
      "handicapSequence": null,
      "handicapPointsSequence": null,
      "handicapStdDev": 0.0,
      "absoluteImprovement": 0.0,
      "parRacer": false
    },
    {
      "originalPlace": 20,
      "canonicalName": "Ondres Lemecka",
      "craftCategory": "M SK",
      "gender": "Unknown",
      "handicap": 1.0,
      "timeSeconds": 9653.3,
      "timeVersusPar": 0.0,
      "adjustedTimeSeconds": 9653.3,
      "adjustedTimeVersusPar": 0.0,
      "adjustedPlace": 0,
      "handicapPost": 1.0,
      "numRaces": 0,
      "handicapSequence": null,
      "handicapPointsSequence": null,
      "handicapStdDev": 0.0,
      "absoluteImprovement": 0.0,
      "parRacer": false
    },
    {
      "originalPlace": 21,
      "canonicalName": "Vratislav Polak",
      "craftCategory": "M SK",
      "gender": "Unknown",
      "handicap": 1.0,
      "timeSeconds": 10751.2,
      "timeVersusPar": 0.0,
      "adjustedTimeSeconds": 10751.2,
      "adjustedTimeVersusPar": 0.0,
      "adjustedPlace": 0,
      "handicapPost": 1.0,
      "numRaces": 0,
      "handicapSequence": null,
      "handicapPointsSequence": null,
      "handicapStdDev": 0.0,
      "absoluteImprovement": 0.0,
      "parRacer": false
    },
    {
      "originalPlace": 22,
      "canonicalName": "Jiri Pertold",
      "craftCategory": "M SK",
      "gender": "Unknown",
      "handicap": 1.0,
      "timeSeconds": 10751.5,
      "timeVersusPar": 0.0,
      "adjustedTimeSeconds": 10751.5,
      "adjustedTimeVersusPar": 0.0,
      "adjustedPlace": 0,
      "handicapPost": 1.0,
      "numRaces": 0,
      "handicapSequence": null,
      "handicapPointsSequence": null,
      "handicapStdDev": 0.0,
      "absoluteImprovement": 0.0,
      "parRacer": false
    },
    {
      "originalPlace": 23,
      "canonicalName": "Carrie Weisse",
      "craftCategory": "W 1x-OWII",
      "gender": "Unknown",
      "handicap": 1.0,
      "timeSeconds": 12191.2,
      "timeVersusPar": 0.0,
      "adjustedTimeSeconds": 12191.2,
      "adjustedTimeVersusPar": 0.0,
      "adjustedPlace": 0,
      "handicapPost": 1.0,
      "numRaces": 0,
      "handicapSequence": null,
      "handicapPointsSequence": null,
      "handicapStdDev": 0.0,
      "absoluteImprovement": 0.0,
      "parRacer": false
    },
    {
      "originalPlace": 24,
      "canonicalName": "Pat Johnson",
      "craftCategory": "W 1x-OWIII",
      "gender": "Unknown",
      "handicap": 1.0,
      "timeSeconds": 12201.2,
      "timeVersusPar": 0.0,
      "adjustedTimeSeconds": 12201.2,
      "adjustedTimeVersusPar": 0.0,
      "adjustedPlace": 0,
      "handicapPost": 1.0,
      "numRaces": 0,
      "handicapSequence": null,
      "handicapPointsSequence": null,
      "handicapStdDev": 0.0,
      "absoluteImprovement": 0.0,
      "parRacer": false
    },
    {
      "originalPlace": 25,
      "canonicalName": "Alan Kipust/Sandra Kipust",
      "craftCategory": "Mx C2",
      "gender": "Unknown",
      "handicap": 1.0,
      "timeSeconds": 13750.0,
      "timeVersusPar": 0.0,
      "adjustedTimeSeconds": 13750.0,
      "adjustedTimeVersusPar": 0.0,
      "adjustedPlace": 0,
      "handicapPost": 1.0,
      "numRaces": 0,
      "handicapSequence": null,
      "handicapPointsSequence": null,
      "handicapStdDev": 0.0,
      "absoluteImprovement": 0.0,
      "parRacer": false
    }
  ]
}