{
  "raceInfo": {
    "raceId": 145513,
    "distance": "Cat 1",
    "name": "BEPC07302018 \u2014 Cat 1",
    "displayURL": "https://www.webscorer.com/race?raceid=145513",
    "date": "Jul 30, 2018",
    "sport": "Paddling - SUP",
    "startTime": "Monday, July 30, 2018 7:15 PM (GMT-7)",
    "country": "United States",
    "city": "Seattle",
    "pointsWeight": 0.692308
  },
  "racerResults": [
    {
      "originalPlace": 1,
      "canonicalName": "Christian Oliver",
      "craftCategory": "SUP 14\u2019",
      "gender": "Male",
      "handicap": 1.0,
      "timeSeconds": 1242.6,
      "timeVersusPar": 0.0,
      "adjustedTimeSeconds": 1242.6,
      "adjustedTimeVersusPar": 0.0,
      "adjustedPlace": 0,
      "handicapPost": 1.0,
      "numRaces": 0,
      "handicapSequence": null,
      "handicapPointsSequence": null,
      "handicapStdDev": 0.0,
      "absoluteImprovement": 0.0,
      "parRacer": false
    },
    {
      "originalPlace": 2,
      "canonicalName": "Alex Vaughan",
      "craftCategory": "SUP 14\u2019",
      "gender": "Male",
      "handicap": 1.0,
      "timeSeconds": 1286.3,
      "timeVersusPar": 0.0,
      "adjustedTimeSeconds": 1286.3,
      "adjustedTimeVersusPar": 0.0,
      "adjustedPlace": 0,
      "handicapPost": 1.0,
      "numRaces": 0,
      "handicapSequence": null,
      "handicapPointsSequence": null,
      "handicapStdDev": 0.0,
      "absoluteImprovement": 0.0,
      "parRacer": false
    },
    {
      "originalPlace": 3,
      "canonicalName": "Bruce Barry",
      "craftCategory": "SUP 14\u2019",
      "gender": "Male",
      "handicap": 1.0,
      "timeSeconds": 1306.4,
      "timeVersusPar": 0.0,
      "adjustedTimeSeconds": 1306.4,
      "adjustedTimeVersusPar": 0.0,
      "adjustedPlace": 0,
      "handicapPost": 1.0,
      "numRaces": 0,
      "handicapSequence": null,
      "handicapPointsSequence": null,
      "handicapStdDev": 0.0,
      "absoluteImprovement": 0.0,
      "parRacer": false
    },
    {
      "originalPlace": 4,
      "canonicalName": "Nick Papa",
      "craftCategory": "SUP 14\u2019",
      "gender": "Male",
      "handicap": 1.0,
      "timeSeconds": 1322.9,
      "timeVersusPar": 0.0,
      "adjustedTimeSeconds": 1322.9,
      "adjustedTimeVersusPar": 0.0,
      "adjustedPlace": 0,
      "handicapPost": 1.0,
      "numRaces": 0,
      "handicapSequence": null,
      "handicapPointsSequence": null,
      "handicapStdDev": 0.0,
      "absoluteImprovement": 0.0,
      "parRacer": false
    },
    {
      "originalPlace": 5,
      "canonicalName": "Sarah Sandstrom",
      "craftCategory": "SUP 14\u2019",
      "gender": "Female",
      "handicap": 1.0,
      "timeSeconds": 1329.6,
      "timeVersusPar": 0.0,
      "adjustedTimeSeconds": 1329.6,
      "adjustedTimeVersusPar": 0.0,
      "adjustedPlace": 0,
      "handicapPost": 1.0,
      "numRaces": 0,
      "handicapSequence": null,
      "handicapPointsSequence": null,
      "handicapStdDev": 0.0,
      "absoluteImprovement": 0.0,
      "parRacer": false
    },
    {
      "originalPlace": 6,
      "canonicalName": "Patrick Hwang",
      "craftCategory": "SUP 14\u2019",
      "gender": "Male",
      "handicap": 1.0,
      "timeSeconds": 1349.6,
      "timeVersusPar": 0.0,
      "adjustedTimeSeconds": 1349.6,
      "adjustedTimeVersusPar": 0.0,
      "adjustedPlace": 0,
      "handicapPost": 1.0,
      "numRaces": 0,
      "handicapSequence": null,
      "handicapPointsSequence": null,
      "handicapStdDev": 0.0,
      "absoluteImprovement": 0.0,
      "parRacer": false
    },
    {
      "originalPlace": 7,
      "canonicalName": "Aaron Thompson",
      "craftCategory": "SUP 14\u2019",
      "gender": "Male",
      "handicap": 1.0,
      "timeSeconds": 1366.7,
      "timeVersusPar": 0.0,
      "adjustedTimeSeconds": 1366.7,
      "adjustedTimeVersusPar": 0.0,
      "adjustedPlace": 0,
      "handicapPost": 1.0,
      "numRaces": 0,
      "handicapSequence": null,
      "handicapPointsSequence": null,
      "handicapStdDev": 0.0,
      "absoluteImprovement": 0.0,
      "parRacer": false
    },
    {
      "originalPlace": 8,
      "canonicalName": "Lance Jorgenson",
      "craftCategory": "SUP 14\u2019",
      "gender": "Male",
      "handicap": 1.0,
      "timeSeconds": 1371.4,
      "timeVersusPar": 0.0,
      "adjustedTimeSeconds": 1371.4,
      "adjustedTimeVersusPar": 0.0,
      "adjustedPlace": 0,
      "handicapPost": 1.0,
      "numRaces": 0,
      "handicapSequence": null,
      "handicapPointsSequence": null,
      "handicapStdDev": 0.0,
      "absoluteImprovement": 0.0,
      "parRacer": false
    },
    {
      "originalPlace": 9,
      "canonicalName": "Chris Grieve",
      "craftCategory": "SUP 14\u2019",
      "gender": "Male",
      "handicap": 1.0,
      "timeSeconds": 1373.0,
      "timeVersusPar": 0.0,
      "adjustedTimeSeconds": 1373.0,
      "adjustedTimeVersusPar": 0.0,
      "adjustedPlace": 0,
      "handicapPost": 1.0,
      "numRaces": 0,
      "handicapSequence": null,
      "handicapPointsSequence": null,
      "handicapStdDev": 0.0,
      "absoluteImprovement": 0.0,
      "parRacer": false
    },
    {
      "originalPlace": 10,
      "canonicalName": "Ivan Storck",
      "craftCategory": "SUP 14\u2019",
      "gender": "Male",
      "handicap": 1.0,
      "timeSeconds": 1381.7,
      "timeVersusPar": 0.0,
      "adjustedTimeSeconds": 1381.7,
      "adjustedTimeVersusPar": 0.0,
      "adjustedPlace": 0,
      "handicapPost": 1.0,
      "numRaces": 0,
      "handicapSequence": null,
      "handicapPointsSequence": null,
      "handicapStdDev": 0.0,
      "absoluteImprovement": 0.0,
      "parRacer": false
    },
    {
      "originalPlace": 11,
      "canonicalName": "Sean Nordquist",
      "craftCategory": "SUP 14\u2019",
      "gender": "Male",
      "handicap": 1.0,
      "timeSeconds": 1390.9,
      "timeVersusPar": 0.0,
      "adjustedTimeSeconds": 1390.9,
      "adjustedTimeVersusPar": 0.0,
      "adjustedPlace": 0,
      "handicapPost": 1.0,
      "numRaces": 0,
      "handicapSequence": null,
      "handicapPointsSequence": null,
      "handicapStdDev": 0.0,
      "absoluteImprovement": 0.0,
      "parRacer": false
    },
    {
      "originalPlace": 12,
      "canonicalName": "Wes Van Wambeck",
      "craftCategory": "SUP 14\u2019",
      "gender": "Male",
      "handicap": 1.0,
      "timeSeconds": 1407.7,
      "timeVersusPar": 0.0,
      "adjustedTimeSeconds": 1407.7,
      "adjustedTimeVersusPar": 0.0,
      "adjustedPlace": 0,
      "handicapPost": 1.0,
      "numRaces": 0,
      "handicapSequence": null,
      "handicapPointsSequence": null,
      "handicapStdDev": 0.0,
      "absoluteImprovement": 0.0,
      "parRacer": false
    },
    {
      "originalPlace": 13,
      "canonicalName": "Adam Kollgaard",
      "craftCategory": "SUP 14\u2019",
      "gender": "Male",
      "handicap": 1.0,
      "timeSeconds": 1416.3,
      "timeVersusPar": 0.0,
      "adjustedTimeSeconds": 1416.3,
      "adjustedTimeVersusPar": 0.0,
      "adjustedPlace": 0,
      "handicapPost": 1.0,
      "numRaces": 0,
      "handicapSequence": null,
      "handicapPointsSequence": null,
      "handicapStdDev": 0.0,
      "absoluteImprovement": 0.0,
      "parRacer": false
    },
    {
      "originalPlace": 14,
      "canonicalName": "Jerimiah Smith",
      "craftCategory": "SUP 14\u2019",
      "gender": "Male",
      "handicap": 1.0,
      "timeSeconds": 1429.0,
      "timeVersusPar": 0.0,
      "adjustedTimeSeconds": 1429.0,
      "adjustedTimeVersusPar": 0.0,
      "adjustedPlace": 0,
      "handicapPost": 1.0,
      "numRaces": 0,
      "handicapSequence": null,
      "handicapPointsSequence": null,
      "handicapStdDev": 0.0,
      "absoluteImprovement": 0.0,
      "parRacer": false
    },
    {
      "originalPlace": 15,
      "canonicalName": "Matt Radford",
      "craftCategory": "SUP 14\u2019",
      "gender": "Male",
      "handicap": 1.0,
      "timeSeconds": 1430.0,
      "timeVersusPar": 0.0,
      "adjustedTimeSeconds": 1430.0,
      "adjustedTimeVersusPar": 0.0,
      "adjustedPlace": 0,
      "handicapPost": 1.0,
      "numRaces": 0,
      "handicapSequence": null,
      "handicapPointsSequence": null,
      "handicapStdDev": 0.0,
      "absoluteImprovement": 0.0,
      "parRacer": false
    },
    {
      "originalPlace": 16,
      "canonicalName": "Levi Goltz",
      "craftCategory": "SUP 14\u2019",
      "gender": "Male",
      "handicap": 1.0,
      "timeSeconds": 1432.0,
      "timeVersusPar": 0.0,
      "adjustedTimeSeconds": 1432.0,
      "adjustedTimeVersusPar": 0.0,
      "adjustedPlace": 0,
      "handicapPost": 1.0,
      "numRaces": 0,
      "handicapSequence": null,
      "handicapPointsSequence": null,
      "handicapStdDev": 0.0,
      "absoluteImprovement": 0.0,
      "parRacer": false
    },
    {
      "originalPlace": 17,
      "canonicalName": "Evan Vernon",
      "craftCategory": "SUP 14\u2019",
      "gender": "Male",
      "handicap": 1.0,
      "timeSeconds": 1479.3,
      "timeVersusPar": 0.0,
      "adjustedTimeSeconds": 1479.3,
      "adjustedTimeVersusPar": 0.0,
      "adjustedPlace": 0,
      "handicapPost": 1.0,
      "numRaces": 0,
      "handicapSequence": null,
      "handicapPointsSequence": null,
      "handicapStdDev": 0.0,
      "absoluteImprovement": 0.0,
      "parRacer": false
    },
    {
      "originalPlace": 18,
      "canonicalName": "Michele Black",
      "craftCategory": "SUP 12\u20196\u201d",
      "gender": "Female",
      "handicap": 1.0,
      "timeSeconds": 1527.1,
      "timeVersusPar": 0.0,
      "adjustedTimeSeconds": 1527.1,
      "adjustedTimeVersusPar": 0.0,
      "adjustedPlace": 0,
      "handicapPost": 1.0,
      "numRaces": 0,
      "handicapSequence": null,
      "handicapPointsSequence": null,
      "handicapStdDev": 0.0,
      "absoluteImprovement": 0.0,
      "parRacer": false
    },
    {
      "originalPlace": 19,
      "canonicalName": "Michael Schutzler",
      "craftCategory": "Prone",
      "gender": "Male",
      "handicap": 1.0,
      "timeSeconds": 1554.2,
      "timeVersusPar": 0.0,
      "adjustedTimeSeconds": 1554.2,
      "adjustedTimeVersusPar": 0.0,
      "adjustedPlace": 0,
      "handicapPost": 1.0,
      "numRaces": 0,
      "handicapSequence": null,
      "handicapPointsSequence": null,
      "handicapStdDev": 0.0,
      "absoluteImprovement": 0.0,
      "parRacer": false
    },
    {
      "originalPlace": 20,
      "canonicalName": "Rob Casey",
      "craftCategory": "SUP 14\u2019",
      "gender": "Male",
      "handicap": 1.0,
      "timeSeconds": 1589.8,
      "timeVersusPar": 0.0,
      "adjustedTimeSeconds": 1589.8,
      "adjustedTimeVersusPar": 0.0,
      "adjustedPlace": 0,
      "handicapPost": 1.0,
      "numRaces": 0,
      "handicapSequence": null,
      "handicapPointsSequence": null,
      "handicapStdDev": 0.0,
      "absoluteImprovement": 0.0,
      "parRacer": false
    },
    {
      "originalPlace": 21,
      "canonicalName": "Robert Te Winkel",
      "craftCategory": "SUP 14\u2019",
      "gender": "Male",
      "handicap": 1.0,
      "timeSeconds": 1694.1,
      "timeVersusPar": 0.0,
      "adjustedTimeSeconds": 1694.1,
      "adjustedTimeVersusPar": 0.0,
      "adjustedPlace": 0,
      "handicapPost": 1.0,
      "numRaces": 0,
      "handicapSequence": null,
      "handicapPointsSequence": null,
      "handicapStdDev": 0.0,
      "absoluteImprovement": 0.0,
      "parRacer": false
    },
    {
      "originalPlace": 22,
      "canonicalName": "Patricia Hughes",
      "craftCategory": "SUP 12\u20196\u201d",
      "gender": "Female",
      "handicap": 1.0,
      "timeSeconds": 1725.0,
      "timeVersusPar": 0.0,
      "adjustedTimeSeconds": 1725.0,
      "adjustedTimeVersusPar": 0.0,
      "adjustedPlace": 0,
      "handicapPost": 1.0,
      "numRaces": 0,
      "handicapSequence": null,
      "handicapPointsSequence": null,
      "handicapStdDev": 0.0,
      "absoluteImprovement": 0.0,
      "parRacer": false
    },
    {
      "originalPlace": 23,
      "canonicalName": "Nathanial Lodwig",
      "craftCategory": "SUP 14\u2019",
      "gender": "Male",
      "handicap": 1.0,
      "timeSeconds": 1762.4,
      "timeVersusPar": 0.0,
      "adjustedTimeSeconds": 1762.4,
      "adjustedTimeVersusPar": 0.0,
      "adjustedPlace": 0,
      "handicapPost": 1.0,
      "numRaces": 0,
      "handicapSequence": null,
      "handicapPointsSequence": null,
      "handicapStdDev": 0.0,
      "absoluteImprovement": 0.0,
      "parRacer": false
    },
    {
      "originalPlace": 24,
      "canonicalName": "Fredrick Lefevre",
      "craftCategory": "SUP 14\u2019",
      "gender": "Male",
      "handicap": 1.0,
      "timeSeconds": 1765.6,
      "timeVersusPar": 0.0,
      "adjustedTimeSeconds": 1765.6,
      "adjustedTimeVersusPar": 0.0,
      "adjustedPlace": 0,
      "handicapPost": 1.0,
      "numRaces": 0,
      "handicapSequence": null,
      "handicapPointsSequence": null,
      "handicapStdDev": 0.0,
      "absoluteImprovement": 0.0,
      "parRacer": false
    },
    {
      "originalPlace": 25,
      "canonicalName": "Jessi Wasson",
      "craftCategory": "SUP 12\u20196\u201d",
      "gender": "Female",
      "handicap": 1.0,
      "timeSeconds": 1926.6,
      "timeVersusPar": 0.0,
      "adjustedTimeSeconds": 1926.6,
      "adjustedTimeVersusPar": 0.0,
      "adjustedPlace": 0,
      "handicapPost": 1.0,
      "numRaces": 0,
      "handicapSequence": null,
      "handicapPointsSequence": null,
      "handicapStdDev": 0.0,
      "absoluteImprovement": 0.0,
      "parRacer": false
    },
    {
      "originalPlace": 26,
      "canonicalName": "Lindsey Thomas",
      "craftCategory": "SUP 12\u20196\u201d",
      "gender": "Female",
      "handicap": 1.0,
      "timeSeconds": 2023.3,
      "timeVersusPar": 0.0,
      "adjustedTimeSeconds": 2023.3,
      "adjustedTimeVersusPar": 0.0,
      "adjustedPlace": 0,
      "handicapPost": 1.0,
      "numRaces": 0,
      "handicapSequence": null,
      "handicapPointsSequence": null,
      "handicapStdDev": 0.0,
      "absoluteImprovement": 0.0,
      "parRacer": false
    },
    {
      "originalPlace": 27,
      "canonicalName": "Julia Comstock-Ross",
      "craftCategory": "SUP 14\u2019",
      "gender": "Female",
      "handicap": 1.0,
      "timeSeconds": 2217.5,
      "timeVersusPar": 0.0,
      "adjustedTimeSeconds": 2217.5,
      "adjustedTimeVersusPar": 0.0,
      "adjustedPlace": 0,
      "handicapPost": 1.0,
      "numRaces": 0,
      "handicapSequence": null,
      "handicapPointsSequence": null,
      "handicapStdDev": 0.0,
      "absoluteImprovement": 0.0,
      "parRacer": false
    }
  ]
}